geopmpy/VERSION
geopmpy/__init__.py
geopmpy/agent.py
geopmpy/endpoint.py
geopmpy/hash.py
geopmpy/io.py
geopmpy/launcher.py
geopmpy/policy_store.py
geopmpy/version.py
geopmpy-3.1.0.dist-info/AUTHORS
geopmpy-3.1.0.dist-info/LICENSE-BSD-3-Clause
geopmpy-3.1.0.dist-info/METADATA
geopmpy-3.1.0.dist-info/WHEEL
geopmpy-3.1.0.dist-info/entry_points.txt
geopmpy-3.1.0.dist-info/top_level.txt
geopmpy-3.1.0.dist-info/RECORD
