Metadata-Version: 2.1
Name: geopmpy
Version: 3.1.0
Summary: GEOPM - Global Extensible Open Power Manager Runtime Tools
Author-email: Christopher Cantalupo <christopher.m.cantalupo@intel.com>, Brad Geltz <brad.geltz@intel.com>
Maintainer-email: Christopher Cantalupo <christopher.m.cantalupo@intel.com>, Brad Geltz <brad.geltz@intel.com>
License: Copyright (c) 2015 - 2024 Intel Corporation
Project-URL: Homepage, https://geopm.github.io
Project-URL: Source, https://github.com/geopm/geopm/
Project-URL: Documentation, https://geopm.github.io/geopmpy.7.html
Keywords: runtime,hardware,telemetry,configuration
Classifier: Development Status :: 5 - Production/Stable
Classifier: License :: OSI Approved :: BSD License
Classifier: Operating System :: POSIX :: Linux
Classifier: Natural Language :: English
Classifier: Topic :: Scientific/Engineering
Classifier: Topic :: Software Development :: Libraries :: Application Frameworks
Classifier: Topic :: System :: Hardware :: Symmetric Multi-processing
Classifier: Topic :: System :: Power (UPS)
Classifier: Programming Language :: Python :: 3
Classifier: Programming Language :: Python :: 3.6
Classifier: Programming Language :: Python :: 3.7
Classifier: Programming Language :: Python :: 3.8
Classifier: Programming Language :: Python :: 3.9
Classifier: Programming Language :: Python :: 3.10
Classifier: Programming Language :: Python :: 3.11
Classifier: Programming Language :: Python :: 3 :: Only
Requires-Python: >=3.6
License-File: LICENSE-BSD-3-Clause
License-File: AUTHORS
Requires-Dist: cffi >=1.14.5
Requires-Dist: cycler >=0.11.0
Requires-Dist: natsort >=8.1.0
Requires-Dist: numpy >=1.19.5
Requires-Dist: pandas >=1.1.5
Requires-Dist: psutil >=5.8.0
Requires-Dist: pyyaml >=6.0.0
Requires-Dist: setuptools >=53.0.0
Requires-Dist: tables >=3.7.0
Requires-Dist: geopmdpy
